drprobe/__init__.py
drprobe/commands.py
drprobe/msaprm.py
drprobe/wavimgprm.py
drprobe_interface-0.1.25.dist-info/METADATA
drprobe_interface-0.1.25.dist-info/RECORD
drprobe_interface-0.1.25.dist-info/WHEEL
drprobe_interface-0.1.25.dist-info/top_level.txt
